pymupdf/libsodochandler.so
pymupdf/pro.py
pymupdf/_pro.so
pymupdf/_pro_build.py
pymupdfpro-1.26.6.dist-info/WHEEL
pymupdfpro-1.26.6.dist-info/METADATA
pymupdfpro-1.26.6.dist-info/COPYING
pymupdfpro-1.26.6.dist-info/RECORD
