Metadata-Version: 2.1
Name: PyMuPDFPro
Version: 1.26.6
Summary: Commercial extensions for PyMuPDF; enables Office document handling, including doc, docx, hwp, hwpx, ppt, pptx, xls, xls, and others. Supports text and table extraction, document conversion and more.
Author: Artifex
Author-email: support@artifex.com
License: Commercial license. See artifex.com for details.
Classifier: Development Status :: 5 - Production/Stable
Classifier: Intended Audience :: Developers
Classifier: Intended Audience :: Information Technology
Classifier: License :: Other/Proprietary License
Classifier: Operating System :: Microsoft :: Windows
Classifier: Operating System :: POSIX :: Linux
Classifier: Programming Language :: C
Classifier: Programming Language :: C++
Classifier: Programming Language :: Python :: 3 :: Only
Classifier: Programming Language :: Python :: Implementation :: CPython
Classifier: Topic :: Utilities
Classifier: Topic :: Multimedia :: Graphics
Classifier: Topic :: Software Development :: Libraries
Requires-Dist: PyMuPDF==1.26.6
Requires-Dist: requests
Requires-Python: >=3.9
